.class public final GeneratedClass
.super java/lang/Object

; Fields

; External methods
; .extern method _numba_get_np_random_state()J
; .extern method _numba_rnd_shuffle(J)V

; Constructor
.method public <init>()V
	aload_0
	invokespecial java/lang/Object/<init>()V
	return
.end method

.method public <clinit>()V
	.limit stack 4
	invokestatic org/maropu/lljvm/runtime/VMemory/resetHeap()V

	; allocate global variables

	; initialise global variables
	return
.end method


.method public static __ZN18numpy_random1_test23numpy_random1_test_2441E(JJJ)I
	lconst_0
	lstore 6
	lconst_0
	lstore 8
	iconst_0
	istore 10
	iconst_0
	istore 11
	lconst_0
	lstore 12
	iconst_0
	istore 14
	lconst_0
	lstore 15
	lconst_0
	lstore 17
	lconst_0
	lstore 19
	iconst_0
	istore 21
	iconst_0
	istore 22
	iconst_0
	istore 23
	iconst_0
	istore 24
	iconst_0
	istore 25
	iconst_0
	istore 26
	iconst_0
	istore 27
	iconst_0
	istore 28
	iconst_0
	istore 29
	iconst_0
	istore 30
	iconst_0
	istore 31
	iconst_0
	istore 32
	iconst_0
	istore 33
	iconst_0
	istore 34
	lconst_0
	lstore 35
	iconst_0
	istore 37
	lconst_0
	lstore 38
	lconst_0
	lstore 40
	lconst_0
	lstore 42
	iconst_0
	istore 44
	iconst_0
	istore 45
	iconst_0
	istore 46
	iconst_0
	istore 47
	iconst_0
	istore 48
	iconst_0
	istore 49
	iconst_0
	istore 50
	iconst_0
	istore 51
	iconst_0
	istore 52
	iconst_0
	istore 53
	iconst_0
	istore 54
	iconst_0
	istore 55
	iconst_0
	istore 56
	dconst_0
	dstore 57
	dconst_0
	dstore 59
	dconst_0
	dstore 61
	dconst_0
	dstore 63
	dconst_0
	dstore 65
begin_method:
	invokestatic org/maropu/lljvm/runtime/VMemory/createStackFrame()V
label1:
;  %.20 = tail call { i32, [624 x i32], i32, double, i32 }* @numba_get_np_random_state()
	.line 1
	ldc ""
	ldc "_numba_get_np_random_state()J"
	invokestatic org/maropu/lljvm/runtime/Function/invoke_i64(Ljava/lang/String;Ljava/lang/String;)J
	lstore 6 ; __20
;  %.213 = bitcast { i32, [624 x i32], i32, double, i32 }* %.20 to i32*
	.line 2
	lload 6 ; __20
	lstore 8 ; __213
;  %.22 = load i32, i32* %.213, align 4
	.line 3
	lload 8 ; __213
	invokestatic org/maropu/lljvm/runtime/VMemory/load_i32(J)I
	istore 10 ; __22
;  %.23 = icmp ugt i32 %.22, 623
	.line 4
	iload 10 ; __22
	sipush 623
	invokestatic org/maropu/lljvm/runtime/Instruction/icmp_ugt(II)Z
	iconst_1
	iand
	istore 11 ; __23
;  br i1 %.23, label %B0.if, label %B0.endif, !prof !0
	.line 5
	iload 11 ; __23
	ifne label2
	iload 10 ; __22
	istore 14 ; __28
	goto label3
label2:
;  %0 = bitcast { i32, [624 x i32], i32, double, i32 }* %.20 to i32*
	.line 6
	lload 6 ; __20
	lstore 12 ; _12
;  tail call void @numba_rnd_shuffle({ i32, [624 x i32], i32, double, i32 }* %.20)
	.line 7
	ldc ""
	ldc "_numba_rnd_shuffle(J)V"
	sipush 8
	invokestatic org/maropu/lljvm/runtime/VMemory/allocateStack(I)J
	dup2
	lload 6 ; __20
	invokestatic org/maropu/lljvm/runtime/VMemory/pack(JJ)J
	pop2
	invokestatic org/maropu/lljvm/runtime/Function/invoke_void(Ljava/lang/String;Ljava/lang/String;J)V
;  store i32 0, i32* %0, align 4
	.line 8
	lload 12 ; _12
	iconst_0
	invokestatic org/maropu/lljvm/runtime/VMemory/store(JI)V
;  br label %B0.endif
	.line 9
	iconst_0
	istore 14 ; __28
	goto label3
label3:
;  %.28 = phi i32 [ 0, %B0.if ], [ %.22, %entry ]
	.line 10
;  %1 = bitcast { i32, [624 x i32], i32, double, i32 }* %.20 to i32*
	.line 11
	lload 6 ; __20
	lstore 15 ; _15
;  %2 = sext i32 %.28 to i64
	.line 12
	iload 14 ; __28
	i2l
	lstore 17 ; _17
;  %.30 = getelementptr inbounds { i32, [624 x i32], i32, double, i32 }, { i32, [624 x i32], i32, double, i32 }* %.20, i64 0, i32 1, i64 %2
	.line 13
	lload 6 ; __20
	ldc2_w 4
	ladd
	ldc2_w 4
	lload 17 ; _17
	lmul
	ladd
	lstore 19 ; __30
;  %.31 = load i32, i32* %.30, align 4
	.line 14
	lload 19 ; __30
	invokestatic org/maropu/lljvm/runtime/VMemory/load_i32(J)I
	istore 21 ; __31
;  %.32 = add i32 %.28, 1
	.line 15
	iload 14 ; __28
	iconst_1
	iadd
	istore 22 ; __32
;  store i32 %.32, i32* %1, align 4
	.line 16
	lload 15 ; _15
	iload 22 ; __32
	invokestatic org/maropu/lljvm/runtime/VMemory/store(JI)V
;  %.34 = lshr i32 %.31, 11
	.line 17
	iload 21 ; __31
	bipush 11
	iushr
	istore 23 ; __34
;  %.35 = xor i32 %.34, %.31
	.line 18
	iload 23 ; __34
	iload 21 ; __31
	ixor
	istore 24 ; __35
;  %.36 = shl i32 %.35, 7
	.line 19
	iload 24 ; __35
	bipush 7
	ishl
	istore 25 ; __36
;  %.37 = and i32 %.36, -1658038656
	.line 20
	iload 25 ; __36
	ldc -1658038656
	iand
	istore 26 ; __37
;  %.38 = xor i32 %.37, %.35
	.line 21
	iload 26 ; __37
	iload 24 ; __35
	ixor
	istore 27 ; __38
;  %.39 = shl i32 %.38, 15
	.line 22
	iload 27 ; __38
	bipush 15
	ishl
	istore 28 ; __39
;  %.40 = and i32 %.39, -272236544
	.line 23
	iload 28 ; __39
	ldc -272236544
	iand
	istore 29 ; __40
;  %.41 = xor i32 %.40, %.38
	.line 24
	iload 29 ; __40
	iload 27 ; __38
	ixor
	istore 30 ; __41
;  %.42 = lshr i32 %.41, 18
	.line 25
	iload 30 ; __41
	bipush 18
	iushr
	istore 31 ; __42
;  %.43 = xor i32 %.42, %.41
	.line 26
	iload 31 ; __42
	iload 30 ; __41
	ixor
	istore 32 ; __43
;  %.44 = lshr i32 %.43, 5
	.line 27
	iload 32 ; __43
	iconst_5
	iushr
	istore 33 ; __44
;  %.47 = icmp ugt i32 %.32, 623
	.line 28
	iload 22 ; __32
	sipush 623
	invokestatic org/maropu/lljvm/runtime/Instruction/icmp_ugt(II)Z
	iconst_1
	iand
	istore 34 ; __47
;  br i1 %.47, label %B0.endif.if, label %B0.endif.endif, !prof !0
	.line 29
	iload 34 ; __47
	ifne label4
	iload 22 ; __32
	istore 37 ; __52
	goto label5
label4:
;  %3 = bitcast { i32, [624 x i32], i32, double, i32 }* %.20 to i32*
	.line 30
	lload 6 ; __20
	lstore 35 ; _35
;  tail call void @numba_rnd_shuffle({ i32, [624 x i32], i32, double, i32 }* nonnull %.20)
	.line 31
	ldc ""
	ldc "_numba_rnd_shuffle(J)V"
	sipush 8
	invokestatic org/maropu/lljvm/runtime/VMemory/allocateStack(I)J
	dup2
	lload 6 ; __20
	invokestatic org/maropu/lljvm/runtime/VMemory/pack(JJ)J
	pop2
	invokestatic org/maropu/lljvm/runtime/Function/invoke_void(Ljava/lang/String;Ljava/lang/String;J)V
;  store i32 0, i32* %3, align 4
	.line 32
	lload 35 ; _35
	iconst_0
	invokestatic org/maropu/lljvm/runtime/VMemory/store(JI)V
;  br label %B0.endif.endif
	.line 33
	iconst_0
	istore 37 ; __52
	goto label5
label5:
;  %.52 = phi i32 [ 0, %B0.endif.if ], [ %.32, %B0.endif ]
	.line 34
;  %4 = bitcast { i32, [624 x i32], i32, double, i32 }* %.20 to i32*
	.line 35
	lload 6 ; __20
	lstore 38 ; _38
;  %5 = sext i32 %.52 to i64
	.line 36
	iload 37 ; __52
	i2l
	lstore 40 ; _40
;  %.54 = getelementptr inbounds { i32, [624 x i32], i32, double, i32 }, { i32, [624 x i32], i32, double, i32 }* %.20, i64 0, i32 1, i64 %5
	.line 37
	lload 6 ; __20
	ldc2_w 4
	ladd
	ldc2_w 4
	lload 40 ; _40
	lmul
	ladd
	lstore 42 ; __54
;  %.55 = load i32, i32* %.54, align 4
	.line 38
	lload 42 ; __54
	invokestatic org/maropu/lljvm/runtime/VMemory/load_i32(J)I
	istore 44 ; __55
;  %.56 = add i32 %.52, 1
	.line 39
	iload 37 ; __52
	iconst_1
	iadd
	istore 45 ; __56
;  store i32 %.56, i32* %4, align 4
	.line 40
	lload 38 ; _38
	iload 45 ; __56
	invokestatic org/maropu/lljvm/runtime/VMemory/store(JI)V
;  %.58 = lshr i32 %.55, 11
	.line 41
	iload 44 ; __55
	bipush 11
	iushr
	istore 46 ; __58
;  %.59 = xor i32 %.58, %.55
	.line 42
	iload 46 ; __58
	iload 44 ; __55
	ixor
	istore 47 ; __59
;  %.60 = shl i32 %.59, 7
	.line 43
	iload 47 ; __59
	bipush 7
	ishl
	istore 48 ; __60
;  %.61 = and i32 %.60, -1658038656
	.line 44
	iload 48 ; __60
	ldc -1658038656
	iand
	istore 49 ; __61
;  %.62 = xor i32 %.61, %.59
	.line 45
	iload 49 ; __61
	iload 47 ; __59
	ixor
	istore 50 ; __62
;  %.63 = shl i32 %.62, 15
	.line 46
	iload 50 ; __62
	bipush 15
	ishl
	istore 51 ; __63
;  %.64 = and i32 %.63, -272236544
	.line 47
	iload 51 ; __63
	ldc -272236544
	iand
	istore 52 ; __64
;  %.65 = xor i32 %.64, %.62
	.line 48
	iload 52 ; __64
	iload 50 ; __62
	ixor
	istore 53 ; __65
;  %.66 = lshr i32 %.65, 18
	.line 49
	iload 53 ; __65
	bipush 18
	iushr
	istore 54 ; __66
;  %.67 = xor i32 %.66, %.65
	.line 50
	iload 54 ; __66
	iload 53 ; __65
	ixor
	istore 55 ; __67
;  %.68 = lshr i32 %.67, 6
	.line 51
	iload 55 ; __67
	bipush 6
	iushr
	istore 56 ; __68
;  %.69 = uitofp i32 %.44 to double
	.line 52
	iload 33 ; __44
	invokestatic org/maropu/lljvm/runtime/Instruction/uitofp_f64(I)D
	dstore 57 ; __69
;  %.70 = uitofp i32 %.68 to double
	.line 53
	iload 56 ; __68
	invokestatic org/maropu/lljvm/runtime/Instruction/uitofp_f64(I)D
	dstore 59 ; __70
;  %.71 = fmul double %.69, 0x4190000000000000
	.line 54
	dload 57 ; __69
	ldc2_w 6.710886e+07
	dmul
	dstore 61 ; __71
;  %.72 = fadd double %.71, %.70
	.line 55
	dload 61 ; __71
	dload 59 ; __70
	dadd
	dstore 63 ; __72
;  %.73 = fmul double %.72, 0x3CA0000000000000
	.line 56
	dload 63 ; __72
	ldc2_w 1.110223e-16
	dmul
	dstore 65 ; __73
;  store double %.73, double* %retptr, align 8
	.line 57
	lload_0 ; _retptr
	dload 65 ; __73
	invokestatic org/maropu/lljvm/runtime/VMemory/store(JD)V
;  ret i32 0
	.line 58
	invokestatic org/maropu/lljvm/runtime/VMemory/destroyStackFrame()V
	iconst_0
	ireturn
	.limit stack 16
	.limit locals 67
end_method:
.end method

.method public static _cfunc__ZN18numpy_random1_test23numpy_random1_test_2441E()D
	lconst_0
	lstore 0
	iconst_0
	istore 2
	dconst_0
	dstore 3
begin_method:
	invokestatic org/maropu/lljvm/runtime/VMemory/createStackFrame()V
label6:
;  %.2 = alloca double, align 8
	.line 59
	bipush 8
	invokestatic org/maropu/lljvm/runtime/VMemory/allocateStack(I)J
	lstore_0 ; __2
;  store double 0.000000e+00, double* %.2, align 8
	.line 60
	lload_0 ; __2
	dconst_0
	invokestatic org/maropu/lljvm/runtime/VMemory/store(JD)V
;  %.4 = call i32 @"_ZN18numpy_random1_test23numpy_random1_test$2441E"(double* nonnull %.2, { i8*, i32 }** undef, i8* undef)
	.line 61
	ldc "GeneratedClass"
	ldc "__ZN18numpy_random1_test23numpy_random1_test_2441E(JJJ)I"
	sipush 24
	invokestatic org/maropu/lljvm/runtime/VMemory/allocateStack(I)J
	dup2
	lload_0 ; __2
	invokestatic org/maropu/lljvm/runtime/VMemory/pack(JJ)J
	lconst_0
	invokestatic org/maropu/lljvm/runtime/VMemory/pack(JJ)J
	lconst_0
	invokestatic org/maropu/lljvm/runtime/VMemory/pack(JJ)J
	pop2
	invokestatic org/maropu/lljvm/runtime/Function/invoke_i32(Ljava/lang/String;Ljava/lang/String;J)I
	istore_2 ; __4
;  %.14 = load double, double* %.2, align 8
	.line 62
	lload_0 ; __2
	invokestatic org/maropu/lljvm/runtime/VMemory/load_f64(J)D
	dstore_3 ; __14
;  ret double %.14
	.line 63
	invokestatic org/maropu/lljvm/runtime/VMemory/destroyStackFrame()V
	dload_3 ; __14
	dreturn
	.limit stack 16
	.limit locals 5
end_method:
.end method

